polyprime/__init__.py
polyprime/cli.py
polyprime/compiler.py
polyprime/runtime.py
polyprime-0.2.0.dist-info/licenses/LICENSE
polyprime-0.2.0.dist-info/METADATA
polyprime-0.2.0.dist-info/WHEEL
polyprime-0.2.0.dist-info/entry_points.txt
polyprime-0.2.0.dist-info/top_level.txt
polyprime-0.2.0.dist-info/RECORD
