Metadata-Version: 2.4
Name: polyprime
Version: 0.2.0
Summary: A multi-paradigm programming language that compiles to Python, JavaScript, and more
Home-page: https://github.com/MichaelCrowe11/polyprime
Author: Michael Benjamin Crowe
Author-email: michael@crowelogic.com
Project-URL: Bug Reports, https://github.com/MichaelCrowe11/polyprime/issues
Project-URL: Source, https://github.com/MichaelCrowe11/polyprime
Keywords: programming-language compiler polyglot code-generator multi-paradigm
Classifier: Development Status :: 3 - Alpha
Classifier: Intended Audience :: Developers
Classifier: Topic :: Software Development :: Compilers
Classifier: Topic :: Software Development :: Code Generators
Classifier: License :: OSI Approved :: MIT License
Classifier: Programming Language :: Python :: 3
Classifier: Programming Language :: Python :: 3.8
Classifier: Programming Language :: Python :: 3.9
Classifier: Programming Language :: Python :: 3.10
Classifier: Programming Language :: Python :: 3.11
Classifier: Programming Language :: Python :: 3.12
Classifier: Operating System :: OS Independent
Requires-Python: >=3.8
License-File: LICENSE
Requires-Dist: click>=8.0
Provides-Extra: dev
Requires-Dist: pytest>=7.0; extra == "dev"
Requires-Dist: black>=23.0; extra == "dev"
Requires-Dist: mypy>=1.0; extra == "dev"
Dynamic: author
Dynamic: author-email
Dynamic: classifier
Dynamic: description
Dynamic: description-content-type
Dynamic: home-page
Dynamic: keywords
Dynamic: license-file
Dynamic: project-url
Dynamic: provides-extra
Dynamic: requires-dist
Dynamic: requires-python
Dynamic: summary
